{
  "id": "1",
  "Black": [
    { "Image": "./images/Black/blackDesktop.jpg" },
    {
      "vertical_1": "./images/BlackVertical/image1.jpg",
      "vertical_2": "./images/BlackVertical/image2.jpg",
      "vertical_3": "./images/BlackVertical/image3.jpg",
      "vertical_4": "./images/BlackVertical/image4.jpg",
      "vertical_5": "./images/BlackVertical/image5.jpg",
      "vertical_6": "./images/BlackVertical/image6.jpg"
    },
    {
      "gorizontal_1": "./images/BlackVertical/image1.jpg",
      "gorizontal_2": "./images/BlackVertical/image2.jpg",
      "gorizontal_3": "./images/BlackVertical/image3.jpg",
      "gorizontal_4": "./images/BlackVertical/image4.jpg",
      "gorizontal_5": "./images/BlackVertical/image5.jpg",
      "gorizontal_6": "./images/BlackVertical/image6.jpg"
    }
  ]
}
